samsam_lib/__init__.py
samsam_lib/compute.py
samsam_lib/greeting.py
samsam_lib/util.py
samsam_lib-0.0.1.dist-info/LICENSE
samsam_lib-0.0.1.dist-info/METADATA
samsam_lib-0.0.1.dist-info/WHEEL
samsam_lib-0.0.1.dist-info/top_level.txt
samsam_lib-0.0.1.dist-info/RECORD
