Metadata-Version: 2.1
Name: samsam-lib
Version: 0.0.1
Summary: A temp package
Home-page: https://github.com/c-tawayip/sam_simple_package
Author: c-tawayip
Author-email: piyawatchuangkrud@gmail.com
License: UNKNOWN
Platform: UNKNOWN
Classifier: License :: OSI Approved :: MIT License
Classifier: Programming Language :: Python :: 3
Classifier: Programming Language :: Python :: 3.8
License-File: LICENSE
